soigne/__init__.py
soigne/container.py
soigne/gamegui.py
soigne/components/__init__.py
soigne/components/configs.py
soigne/components/game.py
soigne/components/l10n.py
soigne-0.1.8b6.dist-info/LICENSE
soigne-0.1.8b6.dist-info/METADATA
soigne-0.1.8b6.dist-info/WHEEL
soigne-0.1.8b6.dist-info/top_level.txt
soigne-0.1.8b6.dist-info/RECORD
